django_remote_auth_ldap/__init__.py
django_remote_auth_ldap/backend.py
django_remote_auth_ldap/conf.py
django_remote_auth_ldap/middleware.py
django_remote_auth_ldap-1.0.0.dist-info/METADATA
django_remote_auth_ldap-1.0.0.dist-info/RECORD
django_remote_auth_ldap-1.0.0.dist-info/WHEEL
django_remote_auth_ldap-1.0.0.dist-info/top_level.txt
