Metadata-Version: 2.1
Name: django-remote-auth-ldap
Version: 1.0.0
Summary: REMOTE_USER authentication using LDAP
Home-page: https://github.com/apmorton/django-remote-auth-ldap
Author: Austin Morton
Author-email: amorton@juvsoft.com
License: MIT
Platform: UNKNOWN
Classifier: Framework :: Django
Classifier: Intended Audience :: Developers
Classifier: License :: OSI Approved :: MIT License
Classifier: Framework :: Django
Classifier: Programming Language :: Python
Classifier: Programming Language :: Python :: 2.7
Classifier: Programming Language :: Python :: 3.4
Classifier: Programming Language :: Python :: 3.5
Classifier: Programming Language :: Python :: 3.6
Classifier: Programming Language :: Python :: 3.7
Classifier: Topic :: Internet :: WWW/HTTP
Requires-Dist: django-auth-ldap
Requires-Dist: django-appconf
